po4/__init__.py
po4/config.py
po4/errors.py
po4/model.py
po4/protocols.py
po4/utils.py
po4/cli/__init__.py
po4/cli/main.py
po4/loaders/__init__.py
po4/loaders/excel.py
po4/stepwise/__init__.py
po4/stepwise/make.py
po4-0.2.0.dist-info/entry_points.txt
po4-0.2.0.dist-info/LICENSE.txt
po4-0.2.0.dist-info/WHEEL
po4-0.2.0.dist-info/METADATA
po4-0.2.0.dist-info/RECORD
