Metadata-Version: 2.1
Name: po4
Version: 0.2.0
Summary: Database of DNA sequences.
Home-page: https://github.com/kalekundert/po4
License: UNKNOWN
Author: Kale Kundert
Author-email: kale@thekunderts.net
Requires-Python: ~=3.8
Classifier: Programming Language :: Python :: 3
Classifier: License :: OSI Approved :: MIT License
Requires-Dist: appdirs
Requires-Dist: autoprop
Requires-Dist: autosnapgene
Requires-Dist: Biopython
Requires-Dist: configurator
Requires-Dist: docopt
Requires-Dist: inform>=1.21
Requires-Dist: more_itertools>=8.0
Requires-Dist: pandas
Requires-Dist: setuptools
Requires-Dist: stepwise
Requires-Dist: stepwise_mol_bio
Requires-Dist: tabulate
Requires-Dist: toml
Requires-Dist: tqdm
Requires-Dist: voluptuous
Requires-Dist: xlrd>=1.0
Requires-Dist: sphinx ; extra == "docs"
Requires-Dist: sphinx_rtd_theme ; extra == "docs"
Requires-Dist: autoclasstoc ; extra == "docs"
Requires-Dist: pytest ; extra == "tests"
Requires-Dist: pytest-cov ; extra == "tests"
Requires-Dist: coveralls ; extra == "tests"
Project-URL: Bug Tracker, https://github.com/kalekundert/phosphatedb/issues
Project-URL: Continuous Integration, https://github.com/kalekundert/phosphatedb/actions
Project-URL: Documentation, https://phosphatedb.readthedocs.io/en/latest/
Project-URL: Test Coverage, https://coveralls.io/github/kalekundert/phosphatedb
Project-URL: Version Control, https://github.com/kalekundert/phosphatedb
Provides-Extra: docs
Provides-Extra: tests
